tensorflow_compression_ops/LICENSE
tensorflow_compression_ops/README.md
tensorflow_compression_ops/__init__.py
tensorflow_compression_ops/cc/libtensorflow_compression.so
tensorflow_compression_ops/tests/__init__.py
tensorflow_compression_ops/tests/all.py
tensorflow_compression_ops/tests/quantization_ops_test.py
tensorflow_compression_ops/tests/range_coding_ops_test.py
tensorflow_compression_ops-2.17.0.dist-info/METADATA
tensorflow_compression_ops-2.17.0.dist-info/WHEEL
tensorflow_compression_ops-2.17.0.dist-info/top_level.txt
tensorflow_compression_ops-2.17.0.dist-info/RECORD
