Metadata-Version: 2.1
Name: tensorflow_compression_ops
Version: 2.17.0
Summary: Data compression ops for TensorFlow
Home-page: https://tensorflow.github.io/compression/
Author: Google LLC
License: Apache 2.0
Project-URL: Documentation, https://tensorflow.github.io/compression/docs/api_docs/python/tfc.html
Project-URL: Discussion, https://groups.google.com/forum/#!forum/tensorflow-compression
Project-URL: Source, https://github.com/tensorflow/compression
Project-URL: Tracker, https://github.com/tensorflow/compression/issues
Keywords: compression data-compression tensorflow machine-learning python deep-learning deep-neural-networks neural-network ml
Classifier: Development Status :: 5 - Production/Stable
Classifier: Intended Audience :: Developers
Classifier: Intended Audience :: Education
Classifier: Intended Audience :: Science/Research
Classifier: License :: OSI Approved :: Apache Software License
Classifier: Programming Language :: Python :: 3
Classifier: Topic :: Scientific/Engineering :: Mathematics
Classifier: Topic :: Software Development :: Libraries :: Python Modules
Classifier: Topic :: Software Development :: Libraries
Requires-Dist: tensorflow~=2.17.0
